slugify/__init__.py
slugify/tests.py
unicode_slugify-0.1.5.dist-info/LICENSE
unicode_slugify-0.1.5.dist-info/METADATA
unicode_slugify-0.1.5.dist-info/WHEEL
unicode_slugify-0.1.5.dist-info/top_level.txt
unicode_slugify-0.1.5.dist-info/RECORD
