Metadata-Version: 2.1
Name: unicode-slugify
Version: 0.1.5
Summary: A slug generator that turns strings into unicode slugs.
Home-page: http://github.com/mozilla/unicode-slugify
Author: Jeff Balogh, Dave Dash
Author-email: jbalogh@mozilla.com, dd@mozilla.com
License: BSD
Platform: UNKNOWN
Classifier: Development Status :: 4 - Beta
Classifier: Environment :: Web Environment
Classifier: Environment :: Web Environment :: Mozilla
Classifier: Intended Audience :: Developers
Classifier: License :: OSI Approved :: BSD License
Classifier: Operating System :: OS Independent
Classifier: Programming Language :: Python
Classifier: Programming Language :: Python :: 2.7
Classifier: Programming Language :: Python :: 3.3
Classifier: Topic :: Software Development :: Libraries :: Python Modules
